drmmsdk/__init__.py
drmmsdk-0.0.5.dist-info/LICENSE
drmmsdk-0.0.5.dist-info/METADATA
drmmsdk-0.0.5.dist-info/WHEEL
drmmsdk-0.0.5.dist-info/top_level.txt
drmmsdk-0.0.5.dist-info/RECORD
