Metadata-Version: 2.1
Name: drmmsdk
Version: 0.0.5
Summary: Datto RMM Unofficial Python SDK
Author: Josh XT
Author-email: josh@devxt.com
Requires-Python: >=3.10
License-File: LICENSE
Requires-Dist: ezsession
Requires-Dist: requests
